visa_vulture/__init__.py
visa_vulture/__main__.py
visa_vulture/main.py
visa_vulture/py.typed
visa_vulture/config/__init__.py
visa_vulture/config/default_config.json
visa_vulture/config/loader.py
visa_vulture/config/schema.py
visa_vulture/file_io/__init__.py
visa_vulture/file_io/results_writer.py
visa_vulture/file_io/test_plan_reader.py
visa_vulture/instruments/__init__.py
visa_vulture/instruments/base_instrument.py
visa_vulture/instruments/power_supply.py
visa_vulture/instruments/signal_generator.py
visa_vulture/instruments/visa_connection.py
visa_vulture/logging_config/__init__.py
visa_vulture/logging_config/setup.py
visa_vulture/model/__init__.py
visa_vulture/model/equipment.py
visa_vulture/model/state_machine.py
visa_vulture/model/test_plan.py
visa_vulture/presenter/__init__.py
visa_vulture/presenter/equipment_presenter.py
visa_vulture/simulation/README.md
visa_vulture/simulation/instruments.yaml
visa_vulture/utils/__init__.py
visa_vulture/utils/threading_helpers.py
visa_vulture/view/__init__.py
visa_vulture/view/log_panel.py
visa_vulture/view/main_window.py
visa_vulture/view/plot_panel.py
visa_vulture/view/resource_manager_dialog.py
visa_vulture/view/test_points_table.py
visa_vulture-0.1.0.dist-info/METADATA
visa_vulture-0.1.0.dist-info/WHEEL
visa_vulture-0.1.0.dist-info/entry_points.txt
visa_vulture-0.1.0.dist-info/licenses/LICENSE
visa_vulture-0.1.0.dist-info/RECORD
