Metadata-Version: 2.4
Name: visa-vulture
Version: 0.1.0
Summary: A Python GUI application for controlling test equipment over VISA
Project-URL: Homepage, https://github.com/dekmeister/visa-vulture
Project-URL: Repository, https://github.com/dekmeister/visa-vulture
Project-URL: Issues, https://github.com/dekmeister/visa-vulture/issues
Author: Declan Walsh
License-Expression: MIT
License-File: LICENSE
Keywords: automation,gui,instrument-control,pyvisa,test-equipment,visa
Classifier: Development Status :: 4 - Beta
Classifier: Environment :: X11 Applications
Classifier: Intended Audience :: Developers
Classifier: Intended Audience :: Science/Research
Classifier: License :: OSI Approved :: MIT License
Classifier: Operating System :: OS Independent
Classifier: Programming Language :: Python :: 3
Classifier: Programming Language :: Python :: 3.10
Classifier: Programming Language :: Python :: 3.11
Classifier: Programming Language :: Python :: 3.12
Classifier: Programming Language :: Python :: 3.13
Classifier: Topic :: Scientific/Engineering
Classifier: Topic :: Scientific/Engineering :: Interface Engine/Protocol Translator
Classifier: Typing :: Typed
Requires-Python: >=3.10
Requires-Dist: matplotlib>=3.7.0
Requires-Dist: pyvisa-sim>=0.5.1
Requires-Dist: pyvisa>=1.13.0
Provides-Extra: dev
Requires-Dist: black>=23.0.0; extra == 'dev'
Requires-Dist: mypy>=1.0.0; extra == 'dev'
Requires-Dist: pytest>=7.0.0; extra == 'dev'
